MerOC/__init__.py
MerOC/__main__.py
MerOC/DATA/LOGO.gif
MerOC-1.1.5.dist-info/LICENSE
MerOC-1.1.5.dist-info/METADATA
MerOC-1.1.5.dist-info/WHEEL
MerOC-1.1.5.dist-info/entry_points.txt
MerOC-1.1.5.dist-info/top_level.txt
MerOC-1.1.5.dist-info/RECORD
