Metadata-Version: 2.1
Name: MerOC
Version: 1.1.5
Summary: Software to download/manipulate netCDF files
Home-page: https://github.com/carmelosammarco/MerOC
Author: Carmelo Sammarco
Author-email: sammarcocarmelo@gmail.com
License: gpl-3.0
Platform: OS Independent
Classifier: Development Status :: 3 - Alpha
Classifier: Intended Audience :: Science/Research
Classifier: Topic :: Scientific/Engineering
Classifier: Programming Language :: Python :: 3.6
Requires-Python: ~=3.6
Requires-Dist: netCDF4 (>=1.4.2)
Requires-Dist: ftputil (>=3.4)
Requires-Dist: motuclient (>=1.8.1)
Requires-Dist: csv342 (>=1.0.0)
Requires-Dist: pandas (>=0.23.4)
Requires-Dist: xarray (>=0.11.0)
Requires-Dist: shapely (>=1.6.4.post1)
Requires-Dist: fiona (>=1.8.4)
Requires-Dist: cdo (>=1.4.0)
